d_flipflop/dff.v
module dff(
    input clk,
    input rst, 
    input d,
    output reg q
);

always @(posedge clk or posedge rst) begin
    if (rst) begin
        q <= 0;
    end else begin
        q <= d;
    end
end
endmodule

d_flipflop/dff_tb.v
// Testbench for D Flip-Flop

module dff_tb;

reg clk;
reg rst;
reg d;
wire q;

// Instantiate the DUT (Device Under Test)
dff uut (
    .clk(clk),
    .rst(rst),
    .d(d),
    .q(q)
);

// Clock generation: 10 time units period
always #5 clk = ~clk;

initial begin
    $dumpfile("dff.vcd");   // VCD file for GTKWave
    $dumpvars(0, dff_tb);   // Dump all signals
end

initial begin
    // Initialize signals
    clk = 0;
    rst = 1;
    d = 0;

    // Apply reset
    #10;
    rst = 0;

    // Test case 1
    #10 d = 1;

    // Test case 2
    #10 d = 0;

    // Test case 3
    #10 d = 1;

    // Apply reset again
    #10 rst = 1;

    #10 rst = 0;
    d = 0;

    #20 d = 1;

    // Finish simulation
    #20;
    $finish;
end

// Monitor signals
initial begin
    $monitor("Time = %0t | clk = %b | rst = %b | d = %b | q = %b",
              $time, clk, rst, d, q);
end

endmodule

d_flipflop/dff.vcd
$date
	Sun Apr 26 00:41:43 2026
$end
$version
	Icarus Verilog
$end
$timescale
	1s
$end
$scope module dff_tb $end
$var wire 1 ! q $end
$var reg 1 " clk $end
$var reg 1 # d $end
$var reg 1 $ rst $end
$scope module uut $end
$var wire 1 " clk $end
$var wire 1 # d $end
$var wire 1 $ rst $end
$var reg 1 ! q $end
$upscope $end
$upscope $end
$enddefinitions $end
$comment Show the parameter values. $end
$dumpall
$end
#0
$dumpvars
1$
0#
0"
0!
$end
#5
1"
#10
0"
0$
#15
1"
#20
0"
1#
#25
1!
1"
#30
0"
0#
#35
0!
1"
#40
0"
1#
#45
1!
1"
#50
0!
0"
1$
#55
1"
#60
0"
0#
0$
#65
1"
#70
0"
#75
1"
#80
0"
1#
#85
1!
1"
