BCD_to_Excess3/module.v
module bcd_to_excess3 (
    input a,b,c,d,
    output w,x,y,z
);

assign z= ~d;
assign y= (c&d)|(~c&~d);
assign x= (~b&c)|(~b&d)|(b&~c&~d);
assign w= a | (b&c) | (b&d);

endmodule

BCD_to_Excess3/module_tb.v
module bcd_to_excess3_tb;

reg a, b, c, d;
wire w, x, y, z;

// Instantiate DUT
bcd_to_excess3 uut (
    .a(a),
    .b(b),
    .c(c),
    .d(d),
    .w(w),
    .x(x),
    .y(y),
    .z(z)
);

// GTKWave dump
initial begin
    $dumpfile("bcd_to_excess3.vcd");
    $dumpvars(0, bcd_to_excess3_tb);
end

// Apply test vectors
initial begin
    $display("Time | a b c d | w x y z");
    $monitor("%4t | %b %b %b %b | %b %b %b %b",
              $time, a, b, c, d, w, x, y, z);

    // Test all valid BCD inputs (0 to 9)

    a=0; b=0; c=0; d=0; #10; // 0 -> 0011
    a=0; b=0; c=0; d=1; #10; // 1 -> 0100
    a=0; b=0; c=1; d=0; #10; // 2 -> 0101
    a=0; b=0; c=1; d=1; #10; // 3 -> 0110
    a=0; b=1; c=0; d=0; #10; // 4 -> 0111
    a=0; b=1; c=0; d=1; #10; // 5 -> 1000
    a=0; b=1; c=1; d=0; #10; // 6 -> 1001
    a=0; b=1; c=1; d=1; #10; // 7 -> 1010
    a=1; b=0; c=0; d=0; #10; // 8 -> 1011
    a=1; b=0; c=0; d=1; #10; // 9 -> 1100

    $finish;
end

endmodule

BCD_to_Excess3/bcd_to_excess3.vcd
$date
	Sun Apr 26 02:12:16 2026
$end
$version
	Icarus Verilog
$end
$timescale
	1s
$end
$scope module bcd_to_excess3_tb $end
$var wire 1 ! z $end
$var wire 1 " y $end
$var wire 1 # x $end
$var wire 1 $ w $end
$var reg 1 % a $end
$var reg 1 & b $end
$var reg 1 ' c $end
$var reg 1 ( d $end
$scope module uut $end
$var wire 1 % a $end
$var wire 1 & b $end
$var wire 1 ' c $end
$var wire 1 ( d $end
$var wire 1 $ w $end
$var wire 1 # x $end
$var wire 1 " y $end
$var wire 1 ! z $end
$upscope $end
$upscope $end
$enddefinitions $end
$comment Show the parameter values. $end
$dumpall
$end
#0
$dumpvars
0(
0'
0&
0%
0$
0#
1"
1!
$end
#10
0"
1#
0!
1(
#20
1!
0(
1'
#30
1"
0!
1(
#40
1!
0(
0'
1&
#50
0"
0#
1$
0!
1(
#60
1!
0(
1'
#70
1"
0!
1(
#80
1!
0(
0'
0&
1%
#90
0"
1#
0!
1(
