ripple_carry_counter/rcc.v
module dff(
    input clk,
    input rst, 
    input d,
    output reg q
);

always @(posedge clk or posedge rst) begin
    if (rst) begin
        q <= 0;
    end else begin
        q <= d;
    end
end
endmodule

module tff(q, clk, rst);
input clk, rst;
output q;
wire d;

dff dff0(clk, rst, d, q);

assign d= ~q;

endmodule

module rcc(q, clk, rst);
input clk, rst;
output [3:0] q;

tff tff0(q[0], clk, rst);
tff tff1(q[1], q[0], rst);
tff tff2(q[2], q[1], rst);
tff tff3(q[3], q[2], rst);

endmodule

ripple_carry_counter/rcc_tb.v
// Testbench for 4-bit Ripple Counter using T Flip-Flops

module rcc_tb;

reg clk;
reg rst;
wire [3:0] q;

// Instantiate DUT
rcc uut (
    .q(q),
    .clk(clk),
    .rst(rst)
);

// Clock generation (10 time units period)
always #5 clk = ~clk;

// GTKWave dump
initial begin
    $dumpfile("rcc.vcd");
    $dumpvars(0, rcc_tb);
end

// Test stimulus
initial begin
    clk = 0;
    rst = 1;

    // Apply reset
    #10 rst = 0;

    // Let counter run
    #100;

    // Apply reset again
    rst = 1;
    #10 rst = 0;

    // Run again
    #50;

    $finish;
end

// Monitor output
initial begin
    $monitor("Time=%0t | rst=%b | q=%b",
              $time, rst, q);
end

endmodule

ripple_carry_counter/rcc.vcd
$date
	Sun Apr 26 01:05:14 2026
$end
$version
	Icarus Verilog
$end
$timescale
	1s
$end
$scope module rcc_tb $end
$var wire 4 ! q [3:0] $end
$var reg 1 " clk $end
$var reg 1 # rst $end
$scope module uut $end
$var wire 1 " clk $end
$var wire 1 # rst $end
$var wire 4 $ q [3:0] $end
$scope module tff0 $end
$var wire 1 " clk $end
$var wire 1 % d $end
$var wire 1 # rst $end
$var wire 1 & q $end
$scope module dff0 $end
$var wire 1 " clk $end
$var wire 1 % d $end
$var wire 1 # rst $end
$var reg 1 & q $end
$upscope $end
$upscope $end
$scope module tff1 $end
$var wire 1 ' clk $end
$var wire 1 ( d $end
$var wire 1 # rst $end
$var wire 1 ) q $end
$scope module dff0 $end
$var wire 1 ' clk $end
$var wire 1 ( d $end
$var wire 1 # rst $end
$var reg 1 ) q $end
$upscope $end
$upscope $end
$scope module tff2 $end
$var wire 1 * clk $end
$var wire 1 + d $end
$var wire 1 # rst $end
$var wire 1 , q $end
$scope module dff0 $end
$var wire 1 * clk $end
$var wire 1 + d $end
$var wire 1 # rst $end
$var reg 1 , q $end
$upscope $end
$upscope $end
$scope module tff3 $end
$var wire 1 - clk $end
$var wire 1 . d $end
$var wire 1 # rst $end
$var wire 1 / q $end
$scope module dff0 $end
$var wire 1 - clk $end
$var wire 1 . d $end
$var wire 1 # rst $end
$var reg 1 / q $end
$upscope $end
$upscope $end
$upscope $end
$upscope $end
$enddefinitions $end
$comment Show the parameter values. $end
$dumpall
$end
#0
$dumpvars
0/
1.
0-
0,
1+
0*
0)
1(
0'
0&
1%
b0 $
1#
0"
b0 !
$end
#5
1"
#10
0"
0#
#15
0.
1/
0+
1-
1,
0(
1*
1)
0%
1'
b1111 !
b1111 $
1&
1"
#20
0"
#25
1%
0'
b1110 !
b1110 $
0&
1"
#30
0"
#35
1(
0*
0)
0%
1'
b1101 !
b1101 $
1&
1"
#40
0"
#45
1%
0'
b1100 !
b1100 $
0&
1"
#50
0"
#55
1+
0-
0,
0(
1*
1)
0%
1'
b1011 !
b1011 $
1&
1"
#60
0"
#65
1%
0'
b1010 !
b1010 $
0&
1"
#70
0"
#75
1(
0*
0)
0%
1'
b1001 !
b1001 $
1&
1"
#80
0"
#85
1%
0'
b1000 !
b1000 $
0&
1"
#90
0"
#95
1.
0/
0+
1-
1,
0(
1*
1)
0%
1'
b111 !
b111 $
1&
1"
#100
0"
#105
1%
0'
b110 !
b110 $
0&
1"
#110
1(
0*
1+
0-
0)
b0 !
b0 $
0,
0"
1#
#115
1"
#120
0"
0#
#125
0.
1/
0+
1-
1,
0(
1*
1)
0%
1'
b1111 !
b1111 $
1&
1"
#130
0"
#135
1%
0'
b1110 !
b1110 $
0&
1"
#140
0"
#145
1(
0*
0)
0%
1'
b1101 !
b1101 $
1&
1"
#150
0"
#155
1%
0'
b1100 !
b1100 $
0&
1"
#160
0"
#165
1+
0-
0,
0(
1*
1)
0%
1'
b1011 !
b1011 $
1&
1"
