8x1Mux_Boolean_function_implementation/module.v
/*
Given:
F = Σm(1,3,4,11,12,13,14)

Truth Table (TT)

a b c d | F
----------------
0 0 0 0 | 0
0 0 0 1 | 1
0 0 1 0 | 0
0 0 1 1 | 1
0 1 0 0 | 1
0 1 0 1 | 0
0 1 1 0 | 0
0 1 1 1 | 0
1 0 0 0 | 0
1 0 0 1 | 0
1 0 1 0 | 0
1 0 1 1 | 1
1 1 0 0 | 1
1 1 0 1 | 1
1 1 1 0 | 1
1 1 1 1 | 0


Grouped in 2 Rows
(Using 8:1 MUX with Select Lines = A, B, C)

A B C | F Expression
---------------------
0 0 0 | D
0 0 1 | D
0 1 0 | D'
0 1 1 | 0
1 0 0 | 0
1 0 1 | D
1 1 0 | 1
1 1 1 | D'


Final MUX Inputs

I0 = D
I1 = D
I2 = D'
I3 = 0
I4 = 0
I5 = D
I6 = 1
I7 = D'

*/

module mux_8to1(i0,i1,i2,i3,i4,i5,i6,i7,s2,s1,s0,y);

input i0,i1,i2,i3,i4,i5,i6,i7,s2,s1,s0;
output y;

wire y0,y1,y2,y3,y4,y5,y6,y7;

assign y0= (i0 & ~s2 & ~s1 & ~s0);
assign y1= (i1 & ~s2 & ~s1 & s0);
assign y2= (i2 & ~s2 & s1 & ~s0);
assign y3= (i3 & ~s2 & s1 & s0);
assign y4= (i4 & s2 & ~s1 & ~s0);
assign y5= (i5 & s2 & ~s1 & s0);
assign y6= (i6 & s2 & s1 & ~s0);
assign y7= (i7 & s2 & s1 & s0);

assign y= (y0 | y1 | y2 | y3 | y4 | y5 | y6 | y7);

endmodule

module func(a,b,c,d,out);
input a,b,c,d;
output out;

mux_8to1 mux1(.i0(d),.i1(d),.i2(~d),.i3(1'b0),.i4(1'b0),.i5(d),.i6(1'b1),.i7(1'b1),.s2(a),.s1(b),.s0(c),.y(out));

endmodule

8x1Mux_Boolean_function_implementation/module_tb.v
// Testbench for function using 8:1 MUX

module func_tb;

reg a, b, c, d;
wire out;

// Instantiate DUT
func uut (
    .a(a),
    .b(b),
    .c(c),
    .d(d),
    .out(out)
);

// GTKWave dump
initial begin
    $dumpfile("func.vcd");
    $dumpvars(0, func_tb);
end

// Apply all input combinations
initial begin
    $display("Time | a b c d | out");
    $monitor("%4t | %b %b %b %b | %b",
              $time, a, b, c, d, out);

    a=0; b=0; c=0; d=0; #10;
    a=0; b=0; c=0; d=1; #10;
    a=0; b=0; c=1; d=0; #10;
    a=0; b=0; c=1; d=1; #10;

    a=0; b=1; c=0; d=0; #10;
    a=0; b=1; c=0; d=1; #10;
    a=0; b=1; c=1; d=0; #10;
    a=0; b=1; c=1; d=1; #10;

    a=1; b=0; c=0; d=0; #10;
    a=1; b=0; c=0; d=1; #10;
    a=1; b=0; c=1; d=0; #10;
    a=1; b=0; c=1; d=1; #10;

    a=1; b=1; c=0; d=0; #10;
    a=1; b=1; c=0; d=1; #10;
    a=1; b=1; c=1; d=0; #10;
    a=1; b=1; c=1; d=1; #10;

    $finish;
end

endmodule

8x1Mux_Boolean_function_implementation/func.vcd
$date
	Sun Apr 26 02:39:30 2026
$end
$version
	Icarus Verilog
$end
$timescale
	1s
$end
$scope module func_tb $end
$var wire 1 ! out $end
$var reg 1 " a $end
$var reg 1 # b $end
$var reg 1 $ c $end
$var reg 1 % d $end
$scope module uut $end
$var wire 1 " a $end
$var wire 1 # b $end
$var wire 1 $ c $end
$var wire 1 % d $end
$var wire 1 ! out $end
$scope module mux1 $end
$var wire 1 % i0 $end
$var wire 1 % i1 $end
$var wire 1 & i2 $end
$var wire 1 ' i3 $end
$var wire 1 ( i4 $end
$var wire 1 % i5 $end
$var wire 1 ) i6 $end
$var wire 1 * i7 $end
$var wire 1 $ s0 $end
$var wire 1 # s1 $end
$var wire 1 " s2 $end
$var wire 1 ! y $end
$var wire 1 + y0 $end
$var wire 1 , y1 $end
$var wire 1 - y2 $end
$var wire 1 . y3 $end
$var wire 1 / y4 $end
$var wire 1 0 y5 $end
$var wire 1 1 y6 $end
$var wire 1 2 y7 $end
$upscope $end
$upscope $end
$upscope $end
$enddefinitions $end
$comment Show the parameter values. $end
$dumpall
$end
#0
$dumpvars
02
01
00
0/
0.
0-
0,
0+
1*
1)
0(
0'
1&
0%
0$
0#
0"
0!
$end
#10
1!
1+
0&
1%
#20
0!
0+
1&
0,
0%
1$
#30
1!
1,
0&
1%
#40
1!
1-
1&
0,
0%
0$
1#
#50
0!
0-
0&
1%
#60
1&
0%
1$
#70
0&
1%
#80
1&
0%
0$
0#
1"
#90
0&
1%
#100
0!
1&
00
0%
1$
#110
1!
10
0&
1%
#120
11
1&
00
0%
0$
1#
#130
0&
1%
#140
01
1&
12
0%
1$
#150
0&
1%
