fulladder/fulladder.v
module halfadder (s,c,x,y);
 
input x, y;
output s,c;

assign s=x^y;
assign c=x&y;

endmodule
//full adder using half adder

module fulladder (s,c,x,y,z);
input x,y,z;
output s,c;
wire s1, d1, d2;
halfadder ha1(s1, d1, x,y);
halfadder ha2(s, d2, s1, z);

assign c=d1 | d2;

endmodule

fulladder/fulladder_tb.v
module fulladder_tb;

  reg x, y, z;     // inputs
  wire s, c;       // outputs

  // instantiate full adder
  fulladder uut (
    .x(x),
    .y(y),
    .z(z),
    .s(s),
    .c(c)
  );

  initial begin
    // VCD dump for waveform
    $dumpfile("fulladder.vcd");
    $dumpvars(0, fulladder_tb);

    // monitor values
    $monitor("t=%0t x=%b y=%b z=%b | sum=%b carry=%b", $time, x, y, z, s, c);

    // test all combinations
    x=0; y=0; z=0; #10;
    x=0; y=0; z=1; #10;
    x=0; y=1; z=0; #10;
    x=0; y=1; z=1; #10;
    x=1; y=0; z=0; #10;
    x=1; y=0; z=1; #10;
    x=1; y=1; z=0; #10;
    x=1; y=1; z=1; #10;

    $finish;
  end

endmodule

fulladder/fulladder.vcd
$date
	Sat Apr 25 01:26:46 2026
$end
$version
	Icarus Verilog
$end
$timescale
	1s
$end
$scope module fulladder_tb $end
$var wire 1 ! s $end
$var wire 1 " c $end
$var reg 1 # x $end
$var reg 1 $ y $end
$var reg 1 % z $end
$scope module uut $end
$var wire 1 " c $end
$var wire 1 # x $end
$var wire 1 $ y $end
$var wire 1 % z $end
$var wire 1 & s1 $end
$var wire 1 ! s $end
$var wire 1 ' d2 $end
$var wire 1 ( d1 $end
$scope module ha1 $end
$var wire 1 ( c $end
$var wire 1 & s $end
$var wire 1 # x $end
$var wire 1 $ y $end
$upscope $end
$scope module ha2 $end
$var wire 1 ' c $end
$var wire 1 ! s $end
$var wire 1 & x $end
$var wire 1 % y $end
$upscope $end
$upscope $end
$upscope $end
$enddefinitions $end
$comment Show the parameter values. $end
$dumpall
$end
#0
$dumpvars
0(
0'
0&
0%
0$
0#
0"
0!
$end
#10
1!
1%
#20
1&
0%
1$
#30
1"
0!
1'
1%
#40
0"
1!
0'
0%
0$
1#
#50
1"
0!
1'
1%
#60
0'
0&
1(
0%
1$
#70
1!
1%
