multiplier/multiplier.v
module multiplier_fourbit(a,b,c);

input [3:0] a;
input [3:0] b;
output [7:0] c;

assign c= a*b;

endmodule

multiplier/multiplier_tb.v
`timescale 1ns/1ps

module multiplier_tb();

reg [3:0] a;
reg [3:0] b;
wire [7:0] c;

multiplier_fourbit DUT(a,b,c);

initial begin
$dumpfile("multiplier.vcd");
$dumpvars(0, multiplier_tb);
$monitor($time, " a=%b, b=%b, c=%b", a, b, c);

// Test Case 
a = 4'b0000;b = 4'b0000; #10;
a = 4'b0000;b = 4'b1111; #10;
a = 4'b0001;b = 4'b0010; #10;
a = 4'b0010;b = 4'b0011; #10;
a = 4'b0011;b = 4'b0100; #10;
a = 4'b0100;b = 4'b0101; #10;
a = 4'b0101;b = 4'b0110; #10;
a = 4'b0110;b = 4'b0111; #10;
a = 4'b0111;b = 4'b1000; #10;
a = 4'b1000;b = 4'b1001; #10;
a = 4'b1001;b = 4'b1010; #10;
a = 4'b1010;b = 4'b1011; #10;
a = 4'b1011;b = 4'b1100; #10;
a = 4'b1100;b = 4'b1101; #10;
a = 4'b1101;b = 4'b1110; #10;
a = 4'b1110;b = 4'b1111; #10;
a = 4'b1111;b = 4'b0001; #10;

$finish;

end

endmodule

multiplier/multiplier.vcd
$date
	Sat Jun 06 01:03:55 2026
$end
$version
	Icarus Verilog
$end
$timescale
	1ps
$end
$scope module multiplier_tb $end
$var wire 8 ! c [7:0] $end
$var reg 4 " a [3:0] $end
$var reg 4 # b [3:0] $end
$scope module DUT $end
$var wire 4 $ a [3:0] $end
$var wire 4 % b [3:0] $end
$var wire 8 & c [7:0] $end
$upscope $end
$upscope $end
$enddefinitions $end
$comment Show the parameter values. $end
$dumpall
$end
#0
$dumpvars
b0 &
b0 %
b0 $
b0 #
b0 "
b0 !
$end
#10000
b1111 #
b1111 %
#20000
b10 #
b10 %
b10 !
b10 &
b1 "
b1 $
#30000
b11 #
b11 %
b110 !
b110 &
b10 "
b10 $
#40000
b100 #
b100 %
b1100 !
b1100 &
b11 "
b11 $
#50000
b101 #
b101 %
b10100 !
b10100 &
b100 "
b100 $
#60000
b110 #
b110 %
b11110 !
b11110 &
b101 "
b101 $
#70000
b111 #
b111 %
b101010 !
b101010 &
b110 "
b110 $
#80000
b1000 #
b1000 %
b111000 !
b111000 &
b111 "
b111 $
#90000
b1001 #
b1001 %
b1001000 !
b1001000 &
b1000 "
b1000 $
#100000
b1010 #
b1010 %
b1011010 !
b1011010 &
b1001 "
b1001 $
#110000
b1011 #
b1011 %
b1101110 !
b1101110 &
b1010 "
b1010 $
#120000
b1100 #
b1100 %
b10000100 !
b10000100 &
b1011 "
b1011 $
#130000
b1101 #
b1101 %
b10011100 !
b10011100 &
b1100 "
b1100 $
#140000
b1110 #
b1110 %
b10110110 !
b10110110 &
b1101 "
b1101 $
#150000
b1111 #
b1111 %
b11010010 !
b11010010 &
b1110 "
b1110 $
#160000
b1 #
b1 %
b1111 !
b1111 &
b1111 "
b1111 $
