fsm_datapath_project/fsm.v
module fsm(
    input LT,
    input LEQ,
    input clk,
    input reset,

    output reg yLoad,
    output reg yClear,
    output reg xLoad,
    output reg xClear,
    output reg iLoad,
    output reg iClear
);

reg [2:0] cState, nState;

always @(posedge clk or posedge reset) begin
    if (reset)
        cState <= 0;
    else
        cState <= nState;
end

always @(*) begin
    yLoad  = 0;
    yClear = 0;
    xLoad  = 0;
    xClear = 0;
    iLoad  = 0;
    iClear = 0;
    nState = 3'b000;

    case(cState)

    3'b000: begin
        xClear = 1;
        iClear = 1;
        nState = 3'b001;
    end

    3'b001: begin
        yLoad = 1;
        xLoad = 1;
        iLoad = 1;
        nState = 3'b010;
    end

    3'b010: begin
        if (LEQ)
            nState = 3'b001;
        else if (LT)
            nState = 3'b011;
        else
            nState = 3'b100;
    end

    default: begin
        nState = 3'b000;
    end

    endcase
end

endmodule

fsm_datapath_project/compareLEQ.v
module compareLEQ #(parameter W = 8)(
    output leq,
    input [W-1:0] a,
    input [W-1:0] b
);

assign leq = (a <= b);

endmodule

fsm_datapath_project/compareLT.v
module compareLT #(parameter W = 8)(
    output lt,
    input [W-1:0] a,
    input [W-1:0] b
);

assign lt = (a < b);

endmodule

fsm_datapath_project/adder.v
module adder #(parameter W = 8)(
    output [W-1:0] sum,
    input [W-1:0] a,
    input [W-1:0] b
);

assign sum = a + b;

endmodule

fsm_datapath_project/register.v
module register #(parameter W = 8)(
    output reg [W-1:0] out,
    input [W-1:0] in,
    input clear,
    input load,
    input clk
);

always @(posedge clk) begin
    if (clear)
        out <= 0;
    else if (load)
        out <= in;
end

endmodule

fsm_datapath_project/sillyComputation.v
module sillyComputation #(parameter W = 8)(
    input clk,
    input reset,
    input [W-1:0] yIn,

    output [W-1:0] x,
    output [W-1:0] y
);

wire [W-1:0] i;
wire [W-1:0] addiOut;
wire [W-1:0] addxOut;

wire yLoad, yClear;
wire xLoad, xClear;
wire iLoad, iClear;

wire xLT0;
wire iLEQ10;

register #(W) I (
    i, addiOut,
    iClear, iLoad, clk
);

register #(W) Y (
    y, yIn,
    yClear, yLoad, clk
);

register #(W) X (
    x, addxOut,
    xClear, xLoad, clk
);

adder #(W) addI (
    addiOut, {{(W-1){1'b0}}, 1'b1}, i
);

adder #(W) addX (
    addxOut, y, x
);

compareLT #(W) cmpX (
    xLT0, x, {W{1'b0}}
);

compareLEQ #(W) cmpI (
    iLEQ10, i, {{(W-4){1'b0}}, 4'd10}
);

fsm control (
    xLT0,
    iLEQ10,
    clk,
    reset,
    yLoad,
    yClear,
    xLoad,
    xClear,
    iLoad,
    iClear
);

endmodule

fsm_datapath_project/sillyComputation_tb.v
// Testbench for sillyComputation (FSM + Datapath)

module sillyComputation_tb;

parameter W = 8;

reg clk;
reg reset;
reg [W-1:0] yIn;

wire [W-1:0] x;
wire [W-1:0] y;

// Instantiate DUT
sillyComputation #(W) uut (
    .clk(clk),
    .reset(reset),
    .yIn(yIn),
    .x(x),
    .y(y)
);

// Clock generation (10 time unit period)
always #5 clk = ~clk;

// GTKWave dump
initial begin
    $dumpfile("output.vcd");
    $dumpvars(0, sillyComputation_tb);
end

// Test stimulus
initial begin
    clk = 0;
    reset = 1;
    yIn = 8'd5;   // Example input value for y

    // Apply reset
    #10;
    reset = 0;

    // Let FSM run
    #200;

    // Change input and test again
    reset = 1;
    #10;
    reset = 0;
    yIn = 8'd3;

    #200;

    $finish;
end

// Monitor signals
initial begin
    $monitor("Time=%0t | reset=%b | yIn=%d | x=%d | y=%d",
              $time, reset, yIn, x, y);
end

endmodule

fsm_datapath_project/output.vcd
$date
	Sun Apr 26 01:50:40 2026
$end
$version
	Icarus Verilog
$end
$timescale
	1s
$end
$scope module sillyComputation_tb $end
$var wire 8 ! y [7:0] $end
$var wire 8 " x [7:0] $end
$var parameter 32 # W $end
$var reg 1 $ clk $end
$var reg 1 % reset $end
$var reg 8 & yIn [7:0] $end
$scope module uut $end
$var wire 1 $ clk $end
$var wire 1 % reset $end
$var wire 8 ' yIn [7:0] $end
$var wire 1 ( yLoad $end
$var wire 1 ) yClear $end
$var wire 8 * y [7:0] $end
$var wire 1 + xLoad $end
$var wire 1 , xLT0 $end
$var wire 1 - xClear $end
$var wire 8 . x [7:0] $end
$var wire 1 / iLoad $end
$var wire 1 0 iLEQ10 $end
$var wire 1 1 iClear $end
$var wire 8 2 i [7:0] $end
$var wire 8 3 addxOut [7:0] $end
$var wire 8 4 addiOut [7:0] $end
$var parameter 32 5 W $end
$scope module I $end
$var wire 1 $ clk $end
$var wire 1 / load $end
$var wire 8 6 in [7:0] $end
$var wire 1 1 clear $end
$var parameter 32 7 W $end
$var reg 8 8 out [7:0] $end
$upscope $end
$scope module X $end
$var wire 1 $ clk $end
$var wire 1 + load $end
$var wire 8 9 in [7:0] $end
$var wire 1 - clear $end
$var parameter 32 : W $end
$var reg 8 ; out [7:0] $end
$upscope $end
$scope module Y $end
$var wire 1 $ clk $end
$var wire 8 < in [7:0] $end
$var wire 1 ( load $end
$var wire 1 ) clear $end
$var parameter 32 = W $end
$var reg 8 > out [7:0] $end
$upscope $end
$scope module addI $end
$var wire 8 ? a [7:0] $end
$var wire 8 @ b [7:0] $end
$var wire 8 A sum [7:0] $end
$var parameter 32 B W $end
$upscope $end
$scope module addX $end
$var wire 8 C a [7:0] $end
$var wire 8 D b [7:0] $end
$var wire 8 E sum [7:0] $end
$var parameter 32 F W $end
$upscope $end
$scope module cmpI $end
$var wire 8 G a [7:0] $end
$var wire 8 H b [7:0] $end
$var wire 1 0 leq $end
$var parameter 32 I W $end
$upscope $end
$scope module cmpX $end
$var wire 8 J a [7:0] $end
$var wire 8 K b [7:0] $end
$var wire 1 , lt $end
$var parameter 32 L W $end
$upscope $end
$scope module control $end
$var wire 1 0 LEQ $end
$var wire 1 , LT $end
$var wire 1 $ clk $end
$var wire 1 % reset $end
$var reg 3 M cState [2:0] $end
$var reg 1 1 iClear $end
$var reg 1 / iLoad $end
$var reg 3 N nState [2:0] $end
$var reg 1 - xClear $end
$var reg 1 + xLoad $end
$var reg 1 ) yClear $end
$var reg 1 ( yLoad $end
$upscope $end
$upscope $end
$upscope $end
$enddefinitions $end
$comment Show the parameter values. $end
$dumpall
b1000 L
b1000 I
b1000 F
b1000 B
b1000 =
b1000 :
b1000 7
b1000 5
b1000 #
$end
#0
$dumpvars
b1 N
b0 M
b0 K
bx J
b1010 H
bx G
bx E
bx D
bx C
bx A
bx @
b1 ?
bx >
b101 <
bx ;
bx 9
bx 8
bx 6
bx 4
bx 3
bx 2
11
x0
0/
bx .
1-
x,
0+
bx *
0)
0(
b101 '
b101 &
1%
0$
bx "
bx !
$end
#5
b1 N
11
1-
b1 4
b1 6
b1 A
10
b0 2
b0 8
b0 @
b0 G
0,
b0 "
b0 .
b0 ;
b0 D
b0 J
1$
#10
0$
0%
#15
1/
1+
1(
b10 N
01
0-
b1 M
1$
#20
0$
#25
b1 N
0/
0+
0(
b10 4
b10 6
b10 A
b1 2
b1 8
b1 @
b1 G
b101 !
b101 *
b101 >
b101 C
x,
bx "
bx .
bx ;
bx D
bx J
b10 M
1$
#30
0$
#35
1/
1+
1(
b10 N
b1 M
1$
#40
0$
#45
b1 N
0/
0+
0(
b11 4
b11 6
b11 A
b10 2
b10 8
b10 @
b10 G
b10 M
1$
#50
0$
#55
1/
1+
1(
b10 N
b1 M
1$
#60
0$
#65
b1 N
0/
0+
0(
b100 4
b100 6
b100 A
b11 2
b11 8
b11 @
b11 G
b10 M
1$
#70
0$
#75
1/
1+
1(
b10 N
b1 M
1$
#80
0$
#85
b1 N
0/
0+
0(
b101 4
b101 6
b101 A
b100 2
b100 8
b100 @
b100 G
b10 M
1$
#90
0$
#95
1/
1+
1(
b10 N
b1 M
1$
#100
0$
#105
b1 N
0/
0+
0(
b110 4
b110 6
b110 A
b101 2
b101 8
b101 @
b101 G
b10 M
1$
#110
0$
#115
1/
1+
1(
b10 N
b1 M
1$
#120
0$
#125
b1 N
0/
0+
0(
b111 4
b111 6
b111 A
b110 2
b110 8
b110 @
b110 G
b10 M
1$
#130
0$
#135
1/
1+
1(
b10 N
b1 M
1$
#140
0$
#145
b1 N
0/
0+
0(
b1000 4
b1000 6
b1000 A
b111 2
b111 8
b111 @
b111 G
b10 M
1$
#150
0$
#155
1/
1+
1(
b10 N
b1 M
1$
#160
0$
#165
b1 N
0/
0+
0(
b1001 4
b1001 6
b1001 A
b1000 2
b1000 8
b1000 @
b1000 G
b10 M
1$
#170
0$
#175
1/
1+
1(
b10 N
b1 M
1$
#180
0$
#185
b1 N
0/
0+
0(
b1010 4
b1010 6
b1010 A
b1001 2
b1001 8
b1001 @
b1001 G
b10 M
1$
#190
0$
#195
1/
1+
1(
b10 N
b1 M
1$
#200
0$
#205
b1 N
0/
0+
0(
b1011 4
b1011 6
b1011 A
b1010 2
b1010 8
b1010 @
b1010 G
b10 M
1$
#210
11
1-
b1 N
b0 M
0$
1%
#215
b1 N
11
1-
b101 3
b101 9
b101 E
0,
b0 "
b0 .
b0 ;
b0 D
b0 J
b1 4
b1 6
b1 A
b0 2
b0 8
b0 @
b0 G
1$
#220
0$
b11 &
b11 '
b11 <
0%
#225
1/
1+
1(
b10 N
01
0-
b1 M
1$
#230
0$
#235
b1 N
0/
0+
0(
b101 "
b101 .
b101 ;
b101 D
b101 J
b1000 3
b1000 9
b1000 E
b11 !
b11 *
b11 >
b11 C
b10 4
b10 6
b10 A
b1 2
b1 8
b1 @
b1 G
b10 M
1$
#240
0$
#245
1/
1+
1(
b10 N
b1 M
1$
#250
0$
#255
b1 N
0/
0+
0(
b1011 3
b1011 9
b1011 E
b1000 "
b1000 .
b1000 ;
b1000 D
b1000 J
b11 4
b11 6
b11 A
b10 2
b10 8
b10 @
b10 G
b10 M
1$
#260
0$
#265
1/
1+
1(
b10 N
b1 M
1$
#270
0$
#275
b1 N
0/
0+
0(
b1110 3
b1110 9
b1110 E
b1011 "
b1011 .
b1011 ;
b1011 D
b1011 J
b100 4
b100 6
b100 A
b11 2
b11 8
b11 @
b11 G
b10 M
1$
#280
0$
#285
1/
1+
1(
b10 N
b1 M
1$
#290
0$
#295
b1 N
0/
0+
0(
b10001 3
b10001 9
b10001 E
b1110 "
b1110 .
b1110 ;
b1110 D
b1110 J
b101 4
b101 6
b101 A
b100 2
b100 8
b100 @
b100 G
b10 M
1$
#300
0$
#305
1/
1+
1(
b10 N
b1 M
1$
#310
0$
#315
b1 N
0/
0+
0(
b10100 3
b10100 9
b10100 E
b10001 "
b10001 .
b10001 ;
b10001 D
b10001 J
b110 4
b110 6
b110 A
b101 2
b101 8
b101 @
b101 G
b10 M
1$
#320
0$
#325
1/
1+
1(
b10 N
b1 M
1$
#330
0$
#335
b1 N
0/
0+
0(
b10111 3
b10111 9
b10111 E
b10100 "
b10100 .
b10100 ;
b10100 D
b10100 J
b111 4
b111 6
b111 A
b110 2
b110 8
b110 @
b110 G
b10 M
1$
#340
0$
#345
1/
1+
1(
b10 N
b1 M
1$
#350
0$
#355
b1 N
0/
0+
0(
b11010 3
b11010 9
b11010 E
b10111 "
b10111 .
b10111 ;
b10111 D
b10111 J
b1000 4
b1000 6
b1000 A
b111 2
b111 8
b111 @
b111 G
b10 M
1$
#360
0$
#365
1/
1+
1(
b10 N
b1 M
1$
#370
0$
#375
b1 N
0/
0+
0(
b11101 3
b11101 9
b11101 E
b11010 "
b11010 .
b11010 ;
b11010 D
b11010 J
b1001 4
b1001 6
b1001 A
b1000 2
b1000 8
b1000 @
b1000 G
b10 M
1$
#380
0$
#385
1/
1+
1(
b10 N
b1 M
1$
#390
0$
#395
b1 N
0/
0+
0(
b100000 3
b100000 9
b100000 E
b11101 "
b11101 .
b11101 ;
b11101 D
b11101 J
b1010 4
b1010 6
b1010 A
b1001 2
b1001 8
b1001 @
b1001 G
b10 M
1$
#400
0$
#405
1/
1+
1(
b10 N
b1 M
1$
#410
0$
#415
b1 N
0/
0+
0(
b100011 3
b100011 9
b100011 E
b100000 "
b100000 .
b100000 ;
b100000 D
b100000 J
b1011 4
b1011 6
b1011 A
b1010 2
b1010 8
b1010 @
b1010 G
b10 M
1$
