Carry_LookAhead_Adder/claAdder.v
//4 bit CLA Adder
module halfadder (s,c,x,y);
input x, y;
output s, c;

assign s=x^y;
assign c=x&y;

endmodule

module carrygenerator (c0,c1,c2,c3,c4,g0,g1,g2,g3,p0,p1,p2,p3);

input c0,g0,g1,g2,g3,p0,p1,p2,p3;   
output c1,c2,c3,c4;

assign c1= (p0 & c0) | g0;
assign c2= g1 | (p1 & g0) | (p1 & p0 & c0);
assign c3= g2 | (p2 & g1) | (p2 & p1 & g0) | (p2 & p1 & p0 & c0);
assign c4= g3 | (p3 & g2) | (p3 & p2 & g1) | (p3 & p2 & p1 & g0) | (p3 & p2 & p1 & p0 & c0);

endmodule

module claAdder(a,b,cin,sum,cout);

input [3:0] a,b;
input cin;
output [3:0] sum;
output cout;

wire p0,p1,p2,p3,g0,g1,g2,g3,c1,c2,c3,c4;

halfadder ha0(p0,g0,a[0],b[0]);
halfadder ha1(p1,g1,a[1],b[1]);
halfadder ha2(p2,g2,a[2],b[2]);
halfadder ha3(p3,g3,a[3],b[3]);

carrygenerator cg(cin,c1,c2,c3,c4,g0,g1,g2,g3,p0,p1,p2,p3);

assign sum[0]= p0 ^ cin;
assign sum[1]= p1 ^ c1;
assign sum[2]= p2 ^ c2;
assign sum[3]= p3 ^ c3;
assign cout= c4;

endmodule

Carry_LookAhead_Adder/claAdder_tb.v
// Testbench for 4-bit CLA Adder

module claAdder_tb;

reg [3:0] a, b;
reg cin;
wire [3:0] sum;
wire cout;

// Instantiate DUT
claAdder uut (
    .a(a),
    .b(b),
    .cin(cin),
    .sum(sum),
    .cout(cout)
);

initial begin
    $dumpfile("claAdder.vcd");
    $dumpvars(0, claAdder_tb);
end

// Apply test vectors
initial begin
    $display("Time |   a   |   b   | cin |  sum  | cout");
    $monitor("%4t | %4b | %4b |  %b  | %4b |  %b",
              $time, a, b, cin, sum, cout);

    // Test cases

    a = 4'b0000; b = 4'b0000; cin = 0; #10;
    a = 4'b0001; b = 4'b0010; cin = 0; #10;
    a = 4'b0101; b = 4'b0011; cin = 0; #10;
    a = 4'b1111; b = 4'b0001; cin = 0; #10;
    a = 4'b1010; b = 4'b0101; cin = 1; #10;
    a = 4'b1111; b = 4'b1111; cin = 1; #10;
    a = 4'b1001; b = 4'b0110; cin = 0; #10;
    a = 4'b0111; b = 4'b1000; cin = 1; #10;

    $finish;
end

endmodule

Carry_LookAhead_Adder/claAdder.vcd
$date
	Sun Apr 26 03:07:29 2026
$end
$version
	Icarus Verilog
$end
$timescale
	1s
$end
$scope module claAdder_tb $end
$var wire 4 ! sum [3:0] $end
$var wire 1 " cout $end
$var reg 4 # a [3:0] $end
$var reg 4 $ b [3:0] $end
$var reg 1 % cin $end
$scope module uut $end
$var wire 4 & a [3:0] $end
$var wire 4 ' b [3:0] $end
$var wire 1 % cin $end
$var wire 1 " cout $end
$var wire 4 ( sum [3:0] $end
$var wire 1 ) p3 $end
$var wire 1 * p2 $end
$var wire 1 + p1 $end
$var wire 1 , p0 $end
$var wire 1 - g3 $end
$var wire 1 . g2 $end
$var wire 1 / g1 $end
$var wire 1 0 g0 $end
$var wire 1 1 c4 $end
$var wire 1 2 c3 $end
$var wire 1 3 c2 $end
$var wire 1 4 c1 $end
$scope module cg $end
$var wire 1 % c0 $end
$var wire 1 4 c1 $end
$var wire 1 3 c2 $end
$var wire 1 2 c3 $end
$var wire 1 1 c4 $end
$var wire 1 ) p3 $end
$var wire 1 * p2 $end
$var wire 1 + p1 $end
$var wire 1 , p0 $end
$var wire 1 - g3 $end
$var wire 1 . g2 $end
$var wire 1 / g1 $end
$var wire 1 0 g0 $end
$upscope $end
$scope module ha0 $end
$var wire 1 0 c $end
$var wire 1 , s $end
$var wire 1 5 x $end
$var wire 1 6 y $end
$upscope $end
$scope module ha1 $end
$var wire 1 / c $end
$var wire 1 + s $end
$var wire 1 7 x $end
$var wire 1 8 y $end
$upscope $end
$scope module ha2 $end
$var wire 1 . c $end
$var wire 1 * s $end
$var wire 1 9 x $end
$var wire 1 : y $end
$upscope $end
$scope module ha3 $end
$var wire 1 - c $end
$var wire 1 ) s $end
$var wire 1 ; x $end
$var wire 1 < y $end
$upscope $end
$upscope $end
$upscope $end
$enddefinitions $end
$comment Show the parameter values. $end
$dumpall
$end
#0
$dumpvars
0<
0;
0:
09
08
07
06
05
04
03
02
01
00
0/
0.
0-
0,
0+
0*
0)
b0 (
b0 '
b0 &
0%
b0 $
b0 #
0"
b0 !
$end
#10
b11 !
b11 (
1+
1,
18
15
b10 $
b10 '
b1 #
b1 &
#20
12
13
14
b1000 !
b1000 (
0,
10
1*
16
19
b11 $
b11 '
b101 #
b101 &
#30
1"
11
b0 !
b0 (
1)
08
17
1;
b1 $
b1 '
b1111 #
b1111 &
#40
14
1,
00
b0 !
b0 (
1:
05
09
1%
b101 $
b101 '
b1010 #
b1010 &
#50
b1111 !
b1111 (
0+
1/
0)
1-
0,
10
0*
1.
18
1<
15
19
b1111 $
b1111 '
b1111 #
b1111 &
#60
0"
01
02
03
04
1,
00
1)
0-
1+
0/
1*
0.
b1111 !
b1111 (
06
0<
07
09
0%
b110 $
b110 '
b1001 #
b1001 &
#70
14
13
12
1"
11
b0 !
b0 (
08
0:
1<
17
19
0;
1%
b1000 $
b1000 '
b111 #
b111 &
