sevensegment/sevensegment.v
module sevensegment (digit,segment);

input [3:0] digit;
output reg [6:0] segment;

always @(*) begin
    
    case (digit)
        4'd0: segment = 7'b1111110;
        4'd1: segment = 7'b0110000;
        4'd2: segment = 7'b1101101;
        4'd3: segment = 7'b1111001;
        4'd4: segment = 7'b0110011;
        4'd5: segment = 7'b1011011;
        4'd6: segment = 7'b1011111;
        4'd7: segment = 7'b1110000;
        4'd8: segment = 7'b1111111;
        4'd9: segment = 7'b1111011;
        default: segment = 7'b0000000;
    endcase
end 
endmodule

sevensegment/sevensegment_tb.v
`timescale 1ns/1ps

module sevensegment_tb();

reg [3:0] digit;
wire [6:0] segment;

sevensegment DUT(digit, segment);
integer i;

initial begin

    $dumpfile ("sevensegment.vcd");
    $dumpvars (0, sevensegment_tb);
    $monitor ($time , " digit = %d, segment= %b", digit, segment); 

    for(i=0;i<10;i=i+1) begin
        digit=i; #10;
    end

    $finish;

end

endmodule

sevensegment/sevensegment.vcd
$date
	Sat Jun 06 01:50:17 2026
$end
$version
	Icarus Verilog
$end
$timescale
	1ps
$end
$scope module sevensegment_tb $end
$var wire 7 ! segment [6:0] $end
$var reg 4 " digit [3:0] $end
$var integer 32 # i [31:0] $end
$scope module DUT $end
$var wire 4 $ digit [3:0] $end
$var reg 7 % segment [6:0] $end
$upscope $end
$upscope $end
$enddefinitions $end
$comment Show the parameter values. $end
$dumpall
$end
#0
$dumpvars
b1111110 %
b0 $
b0 #
b0 "
b1111110 !
$end
#10000
b110000 !
b110000 %
b1 "
b1 $
b1 #
#20000
b1101101 !
b1101101 %
b10 "
b10 $
b10 #
#30000
b1111001 !
b1111001 %
b11 "
b11 $
b11 #
#40000
b110011 !
b110011 %
b100 "
b100 $
b100 #
#50000
b1011011 !
b1011011 %
b101 "
b101 $
b101 #
#60000
b1011111 !
b1011111 %
b110 "
b110 $
b110 #
#70000
b1110000 !
b1110000 %
b111 "
b111 $
b111 #
#80000
b1111111 !
b1111111 %
b1000 "
b1000 $
b1000 #
#90000
b1111011 !
b1111011 %
b1001 "
b1001 $
b1001 #
#100000
b1010 #
