ParityGenerator/parity.v
module four_bit_parity(a,b,c,d,p);

input a,b,c,d;
output p;

assign p=(a^b)^(c^d);

endmodule

ParityGenerator/parity_tb.v
// Testbench for 4-bit Parity Generator

module parity_tb;

reg a, b, c, d;
wire p;

// Instantiate DUT
four_bit_parity uut (
    .a(a),
    .b(b),
    .c(c),
    .d(d),
    .p(p)
);

// GTKWave dump
initial begin
    $dumpfile("parity.vcd");
    $dumpvars(0, parity_tb);
end

// Apply test vectors
initial begin
    $display("Time | a b c d | p");
    $monitor("%4t | %b %b %b %b | %b",
              $time, a, b, c, d, p);

    // Test all 16 input combinations

    a=0; b=0; c=0; d=0; #10;
    a=0; b=0; c=0; d=1; #10;
    a=0; b=0; c=1; d=0; #10;
    a=0; b=0; c=1; d=1; #10;
    a=0; b=1; c=0; d=0; #10;
    a=0; b=1; c=0; d=1; #10;
    a=0; b=1; c=1; d=0; #10;
    a=0; b=1; c=1; d=1; #10;
    a=1; b=0; c=0; d=0; #10;
    a=1; b=0; c=0; d=1; #10;
    a=1; b=0; c=1; d=0; #10;
    a=1; b=0; c=1; d=1; #10;
    a=1; b=1; c=0; d=0; #10;
    a=1; b=1; c=0; d=1; #10;
    a=1; b=1; c=1; d=0; #10;
    a=1; b=1; c=1; d=1; #10;

    $finish;
end

endmodule

ParityGenerator/parity.vcd
$date
	Sun Apr 26 02:20:29 2026
$end
$version
	Icarus Verilog
$end
$timescale
	1s
$end
$scope module parity_tb $end
$var wire 1 ! p $end
$var reg 1 " a $end
$var reg 1 # b $end
$var reg 1 $ c $end
$var reg 1 % d $end
$scope module uut $end
$var wire 1 " a $end
$var wire 1 # b $end
$var wire 1 $ c $end
$var wire 1 % d $end
$var wire 1 ! p $end
$upscope $end
$upscope $end
$enddefinitions $end
$comment Show the parameter values. $end
$dumpall
$end
#0
$dumpvars
0%
0$
0#
0"
0!
$end
#10
1!
1%
#20
0%
1$
#30
0!
1%
#40
1!
0%
0$
1#
#50
0!
1%
#60
0%
1$
#70
1!
1%
#80
0%
0$
0#
1"
#90
0!
1%
#100
0%
1$
#110
1!
1%
#120
0!
0%
0$
1#
#130
1!
1%
#140
0%
1$
#150
0!
1%
