jkff/jkff.v
module jk_ff(input j, input k, input clk, output reg q);
  always @ (posedge clk)
    case ({j,k})
      2'b00 : q <= q;
      2'b01 : q <= 0;
      2'b10 : q <= 1;
      2'b11 : q <= ~q;
    endcase
endmodule

jkff/jkff_tb.v
module jk_ff_tb;

reg j, k, clk;
wire q;

jk_ff uut (.j(j), .k(k), .clk(clk), .q(q));

// Clock: period = 10
initial clk = 0;
always #5 clk = ~clk;

// VCD dump
initial begin
    $dumpfile("jk_ff_output.vcd");
    $dumpvars(0, jk_ff_tb);
end

// Monitor
initial $monitor("Time=%3t | clk=%b | j=%b k=%b | q=%b", $time, clk, j, k, q);

task apply;
    input tj, tk;
    begin
        j = tj; k = tk;
        @(posedge clk); #1;
    end
endtask

task check;
    input exp_q;
    input [8*16-1:0] label;
    begin
        if (q !== exp_q)
            $display("FAIL: %s | Expected q=%b, Got q=%b", label, exp_q, q);
        else
            $display("PASS: %s | q=%b", label, q);
    end
endtask

initial begin
    j = 0; k = 0;
    #3;

    apply(0, 1); check(0, "RESET J=0,K=1    ");
    apply(1, 0); check(1, "SET   J=1,K=0    ");
    apply(0, 0); check(1, "HOLD  J=0,K=0 Q=1");
    apply(0, 1); check(0, "RESET J=0,K=1    ");
    apply(0, 0); check(0, "HOLD  J=0,K=0 Q=0");
    apply(1, 1); check(1, "TOGGLE 0->1      ");
    apply(1, 1); check(0, "TOGGLE 1->0      ");
    apply(1, 1); check(1, "TOGGLE 0->1      ");

    $display("=== All tests done ===");
    #10; $finish;
end

endmodule

jkff/jk_ff_output.vcd
$date
	Sun Apr 26 03:48:14 2026
$end
$version
	Icarus Verilog
$end
$timescale
	1s
$end
$scope module jk_ff_tb $end
$var wire 1 ! q $end
$var reg 1 " clk $end
$var reg 1 # j $end
$var reg 1 $ k $end
$scope module uut $end
$var wire 1 " clk $end
$var wire 1 # j $end
$var wire 1 $ k $end
$var reg 1 ! q $end
$upscope $end
$scope task apply $end
$var reg 1 % tj $end
$var reg 1 & tk $end
$upscope $end
$scope task check $end
$var reg 1 ' exp_q $end
$var reg 128 ( label [127:0] $end
$upscope $end
$upscope $end
$enddefinitions $end
$comment Show the parameter values. $end
$dumpall
$end
#0
$dumpvars
bx (
x'
x&
x%
0$
0#
0"
x!
$end
#3
1$
1&
0%
#5
0!
1"
#6
0$
1#
0&
1%
b1000101010100110100010101010100001000000100101000111101001100000010110001001011001111010011000100100000001000000010000000100000 (
0'
#10
0"
#15
1!
1"
#16
0#
0%
b1000101010101000010000000100000001000000100101000111101001100010010110001001011001111010011000000100000001000000010000000100000 (
1'
#20
0"
#25
1"
#26
1$
1&
b1001111010011000100010000100000001000000100101000111101001100000010110001001011001111010011000000100000010100010011110100110001 (
#30
0"
#35
0!
1"
#36
0$
0&
b1000101010100110100010101010100001000000100101000111101001100000010110001001011001111010011000100100000001000000010000000100000 (
0'
#40
0"
#45
1"
#46
1$
1#
1&
1%
b1001111010011000100010000100000001000000100101000111101001100000010110001001011001111010011000000100000010100010011110100110000 (
#50
0"
#55
1!
1"
#56
b1001111010001110100011101001100010001010010000000110000001011010011111000110001001000000010000000100000001000000010000000100000 (
1'
#60
0"
#65
0!
1"
#66
b1001111010001110100011101001100010001010010000000110001001011010011111000110000001000000010000000100000001000000010000000100000 (
0'
#70
0"
#75
1!
1"
#76
b1001111010001110100011101001100010001010010000000110000001011010011111000110001001000000010000000100000001000000010000000100000 (
1'
#80
0"
#85
0!
1"
