graycodeconverter/graycode.v
module graycode_converter(
    input [3:0] a,
    output [3:0] g);

assign g = a ^ (a >> 1);

endmodule

graycodeconverter/graycode_tb.v
`timescale 1ns/1ps

module graycode_tb();

reg [3:0] a;
wire [3:0] g;

graycode_converter DUT(a,g);

initial begin
    $dumpfile("graycode.vcd");
    $dumpvars(0, graycode_tb);
    $monitor($time, " a=%b, g=%b", a, g);

    //test cases
    a = 4'b0000; #10;
    a = 4'b0001; #10;
    a = 4'b0010; #10;
    a = 4'b0011; #10;
    a = 4'b0100; #10;
    a = 4'b0101; #10;
    a = 4'b0110; #10;
    a = 4'b0111; #10;
    a = 4'b1000; #10;
    a = 4'b1001; #10;
    a = 4'b1010; #10;
    a = 4'b1011; #10;
    a = 4'b1100; #10;
    a = 4'b1101; #10;
    a = 4'b1110; #10;
    a = 4'b1111; #10;

    $finish;
    end
endmodule

graycodeconverter/graycode.vcd
$date
	Sat Jun 06 01:16:30 2026
$end
$version
	Icarus Verilog
$end
$timescale
	1ps
$end
$scope module graycode_tb $end
$var wire 4 ! g [3:0] $end
$var reg 4 " a [3:0] $end
$scope module DUT $end
$var wire 4 # a [3:0] $end
$var wire 4 $ g [3:0] $end
$upscope $end
$upscope $end
$enddefinitions $end
$comment Show the parameter values. $end
$dumpall
$end
#0
$dumpvars
b0 $
b0 #
b0 "
b0 !
$end
#10000
b1 !
b1 $
b1 "
b1 #
#20000
b11 !
b11 $
b10 "
b10 #
#30000
b10 !
b10 $
b11 "
b11 #
#40000
b110 !
b110 $
b100 "
b100 #
#50000
b111 !
b111 $
b101 "
b101 #
#60000
b101 !
b101 $
b110 "
b110 #
#70000
b100 !
b100 $
b111 "
b111 #
#80000
b1100 !
b1100 $
b1000 "
b1000 #
#90000
b1101 !
b1101 $
b1001 "
b1001 #
#100000
b1111 !
b1111 $
b1010 "
b1010 #
#110000
b1110 !
b1110 $
b1011 "
b1011 #
#120000
b1010 !
b1010 $
b1100 "
b1100 #
#130000
b1011 !
b1011 $
b1101 "
b1101 #
#140000
b1001 !
b1001 $
b1110 "
b1110 #
#150000
b1000 !
b1000 $
b1111 "
b1111 #
