decoder/decoder.v
//3:8 decoder
module decoder(
    input a,b,c,
    output [7:0] out
);

assign out[0]= (~a & ~b & ~c);
assign out[1]= (~a & ~b & c);
assign out[2]= (~a & b & ~c);
assign out[3]= (~a & b & c);
assign out[4]= (a & ~b & ~c);
assign out[5]= (a & ~b & c);
assign out[6]= (a & b & ~c);
assign out[7]= (a & b & c);
endmodule

decoder/decoder_tb.v
// Testbench for 3:8 Decoder

module decoder_tb;

reg a, b, c;
wire [7:0] out;   

// Instantiate DUT
decoder uut (
    .a(a),
    .b(b),
    .c(c),
    .out(out)
);

initial begin
    $dumpfile("decoder.vcd");
    $dumpvars(0, decoder_tb);
end

// Apply all input combinations
initial begin
    $display("Time | a b c | out");
    $monitor("%4t | %b %b %b | %b",
              $time, a, b, c, out);

    a = 0; b = 0; c = 0; #10;
    a = 0; b = 0; c = 1; #10;
    a = 0; b = 1; c = 0; #10;
    a = 0; b = 1; c = 1; #10;
    a = 1; b = 0; c = 0; #10;
    a = 1; b = 0; c = 1; #10;
    a = 1; b = 1; c = 0; #10;
    a = 1; b = 1; c = 1; #10;

    $finish;
end

endmodule

decoder/decoder.vcd
$date
	Sun Apr 26 02:47:23 2026
$end
$version
	Icarus Verilog
$end
$timescale
	1s
$end
$scope module decoder_tb $end
$var wire 8 ! out [7:0] $end
$var reg 1 " a $end
$var reg 1 # b $end
$var reg 1 $ c $end
$scope module uut $end
$var wire 1 " a $end
$var wire 1 # b $end
$var wire 1 $ c $end
$var wire 8 % out [7:0] $end
$upscope $end
$upscope $end
$enddefinitions $end
$comment Show the parameter values. $end
$dumpall
$end
#0
$dumpvars
b1 %
0$
0#
0"
b1 !
$end
#10
b10 !
b10 %
1$
#20
b100 !
b100 %
0$
1#
#30
b1000 !
b1000 %
1$
#40
b10000 !
b10000 %
0$
0#
1"
#50
b100000 !
b100000 %
1$
#60
b1000000 !
b1000000 %
0$
1#
#70
b10000000 !
b10000000 %
1$
