t_flipflop/tff.v
module dff(
    input clk,
    input rst, 
    input d,
    output reg q
);

always @(posedge clk or posedge rst) begin
    if (rst) begin
        q <= 0;
    end else begin
        q <= d;
    end
end
endmodule

module tff(q, clk, rst);

input clk, rst;
output q;
wire d;
dff dff0(clk, rst, d, q);

assign d= ~q;

endmodule

t_flipflop/tff_tb.v
// Testbench for T Flip-Flop

module tff_tb;

reg clk;
reg rst;
wire q;

// Instantiate DUT
tff uut (
    .q(q),
    .clk(clk),
    .rst(rst)
);

// Clock generation (10 time units period)
always #5 clk = ~clk;

// GTKWave dump
initial begin
    $dumpfile("tff.vcd");
    $dumpvars(0, tff_tb);
end

// Test stimulus
initial begin
    clk = 0;
    rst = 1;

    // Apply reset
    #10 rst = 0;

    // Let T-FF toggle for some clock cycles
    #60;

    // Apply reset again
    rst = 1;
    #10 rst = 0;

    // Run again
    #40;

    $finish;
end

// Monitor signals
initial begin
    $monitor("Time=%0t | clk=%b | rst=%b | q=%b",
              $time, clk, rst, q);
end

endmodule

t_flipflop/tff.vcd
$date
	Sun Apr 26 00:54:22 2026
$end
$version
	Icarus Verilog
$end
$timescale
	1s
$end
$scope module tff_tb $end
$var wire 1 ! q $end
$var reg 1 " clk $end
$var reg 1 # rst $end
$scope module uut $end
$var wire 1 " clk $end
$var wire 1 $ d $end
$var wire 1 # rst $end
$var wire 1 ! q $end
$scope module dff0 $end
$var wire 1 " clk $end
$var wire 1 $ d $end
$var wire 1 # rst $end
$var reg 1 ! q $end
$upscope $end
$upscope $end
$upscope $end
$enddefinitions $end
$comment Show the parameter values. $end
$dumpall
$end
#0
$dumpvars
1$
1#
0"
0!
$end
#5
1"
#10
0"
0#
#15
0$
1!
1"
#20
0"
#25
1$
0!
1"
#30
0"
#35
0$
1!
1"
#40
0"
#45
1$
0!
1"
#50
0"
#55
0$
1!
1"
#60
0"
#65
1$
0!
1"
#70
0"
1#
#75
1"
#80
0"
0#
#85
0$
1!
1"
#90
0"
#95
1$
0!
1"
#100
0"
#105
0$
1!
1"
#110
0"
#115
1$
0!
1"
