simpleckt/simpleckt.v
module simpleckt(x,y,a,b,c);
input a,b,c;
wire e;
output x,y;

and g1(e,a,b);
not g2(y,c);
or g3 (x,e,y);
endmodule

simpleckt/simpleckt_tb.v
`timescale 1ns/1ps

module simpleckt_tb;
  reg a;
  reg b;
  reg c;
  wire x;
  wire y;

  simpleckt dut (
    .x(x),
    .y(y),
    .a(a),
    .b(b),
    .c(c)
  );

  initial begin
    
    $dumpfile("dump.vcd");
    $dumpvars(0, simpleckt_tb);

    $monitor("t=%0t a=%b b=%b c=%b | x=%b y=%b", $time, a, b, c, x, y);

    a = 0; b = 0; c = 0; #10;
    a = 0; b = 0; c = 1; #10;
    a = 0; b = 1; c = 0; #10;
    a = 0; b = 1; c = 1; #10;
    a = 1; b = 0; c = 0; #10;
    a = 1; b = 0; c = 1; #10;
    a = 1; b = 1; c = 0; #10;
    a = 1; b = 1; c = 1; #10;

    $finish;
  end
endmodule

simpleckt/dump.vcd
$date
	Sat Apr 25 01:00:45 2026
$end
$version
	Icarus Verilog
$end
$timescale
	1ps
$end
$scope module simpleckt_tb $end
$var wire 1 ! y $end
$var wire 1 " x $end
$var reg 1 # a $end
$var reg 1 $ b $end
$var reg 1 % c $end
$scope module dut $end
$var wire 1 # a $end
$var wire 1 $ b $end
$var wire 1 % c $end
$var wire 1 & e $end
$var wire 1 " x $end
$var wire 1 ! y $end
$upscope $end
$upscope $end
$enddefinitions $end
$comment Show the parameter values. $end
$dumpall
$end
#0
$dumpvars
0&
0%
0$
0#
1"
1!
$end
#10000
0"
0!
1%
#20000
1"
1!
0%
1$
#30000
0"
0!
1%
#40000
1"
1!
0%
0$
1#
#50000
0"
0!
1%
#60000
1"
1!
1&
0%
1$
#70000
0!
1%
