priorityencoder/pencoder.v
module priorityencoder (
    input p0,p1,p2,p3,p4,p5,p6,p7,
    output z1,z2,z4
);

assign z1= (p1 & ~p2 & ~p4 & ~p6) | (p3 & ~p4 & ~p6) | (p5 & ~p6) | p7;
assign z2= (p2 & ~p4 & ~p5) | (p3 & ~p4 & ~p5) | p6 | p7;
assign z4= p4 | p5 | p6 | p7;

endmodule

priorityencoder/pencoder_tb.v
module pencoder_tb;

  reg [7:0] p;
  wire z1, z2, z4;

  // connect bits
  priorityencoder uut (
    .p0(p[0]), .p1(p[1]), .p2(p[2]), .p3(p[3]),
    .p4(p[4]), .p5(p[5]), .p6(p[6]), .p7(p[7]),
    .z1(z1), .z2(z2), .z4(z4)
  );

  initial begin
    $dumpfile("pencoder.vcd");
    $dumpvars(0, pencoder_tb);

    $monitor("t=%0t p=%b | z=%b%b%b", $time, p, z4, z2, z1);

    p=8'b00000001; #10; // p0
    p=8'b00000010; #10; // p1
    p=8'b00000100; #10; // p2
    p=8'b00001000; #10; // p3
    p=8'b00010000; #10; // p4
    p=8'b00100000; #10; // p5
    p=8'b01000000; #10; // p6
    p=8'b10000000; #10; // p7

    // multiple inputs (priority check)
    p=8'b10101010; #10; // should pick p7
    p=8'b00110000; #10; // should pick p5

    #10 $finish;
  end

endmodule

priorityencoder/pencoder.vcd
$date
	Sat Apr 25 12:54:40 2026
$end
$version
	Icarus Verilog
$end
$timescale
	1s
$end
$scope module pencoder_tb $end
$var wire 1 ! z4 $end
$var wire 1 " z2 $end
$var wire 1 # z1 $end
$var reg 8 $ p [7:0] $end
$scope module uut $end
$var wire 1 % p0 $end
$var wire 1 & p1 $end
$var wire 1 ' p2 $end
$var wire 1 ( p3 $end
$var wire 1 ) p4 $end
$var wire 1 * p5 $end
$var wire 1 + p6 $end
$var wire 1 , p7 $end
$var wire 1 # z1 $end
$var wire 1 " z2 $end
$var wire 1 ! z4 $end
$upscope $end
$upscope $end
$enddefinitions $end
$comment Show the parameter values. $end
$dumpall
$end
#0
$dumpvars
0,
0+
0*
0)
0(
0'
0&
1%
b1 $
0#
0"
0!
$end
#10
1#
0%
1&
b10 $
#20
0#
1"
0&
1'
b100 $
#30
1#
0'
1(
b1000 $
#40
0#
0"
1!
0(
1)
b10000 $
#50
1#
0)
1*
b100000 $
#60
0#
1"
0*
1+
b1000000 $
#70
1#
0+
1,
b10000000 $
#80
1&
1(
1*
b10101010 $
#90
0"
0&
0(
1)
0,
b110000 $
