Alu/alu.v
//alu code

module alu (
input [7:0] A,
input [7:0] B,
input [1:0] S,
output reg [7:0] R
);

wire [7:0] add_out;
wire [7:0] sub_out;
wire [7:0] and_out;
wire [7:0] or_out;

assign add_out= A + B;
assign sub_out= A - B;
assign and_out= A & B;
assign or_out= A | B;

always @(*) begin

if (S== 2'b00)
R = add_out;

else if (S== 2'b01)
R = sub_out;

else if (S== 2'b10)
R = and_out;

else
R = or_out;
end

endmodule

Alu/alu_tb.v
//testbench code
module alu_tb;

reg [7:0] A;
reg [7:0] B;
reg [1:0] S;

wire [7:0] R;

// Instantiate DUT
alu uut (
.A(A),
.B(B),
.S(S),
.R(R)
);

initial begin
$dumpfile("alu.vcd");
$dumpvars(0, alu_tb);
end

initial begin

// Test Case 1
A = 8'd10;
B = 8'd5;

S = 2'b00; // ADD
#10;

S = 2'b01; // SUB
#10;

S = 2'b10; // AND
#10;

S = 2'b11; // OR
#10;

// Test Case 2
A = 8'd12;
B = 8'd3;

S = 2'b00;
#10;

S = 2'b01;
#10;

S = 2'b10;
#10;

S = 2'b11;
#10;

// Test Case 3
A = 8'd15;
B = 8'd15;

S = 2'b00;
#10;

S = 2'b01;
#10;

S = 2'b10;
#10;

S = 2'b11;
#10;

$finish;

end

initial begin
$monitor("Time=%0t | A=%d | B=%d | S=%b | R=%d",
$time, A, B, S, R);
end

endmodule

Alu/alu.vcd
$date
	Sat Jun 06 00:29:53 2026
$end
$version
	Icarus Verilog
$end
$timescale
	1s
$end
$scope module alu_tb $end
$var wire 8 ! R [7:0] $end
$var reg 8 " A [7:0] $end
$var reg 8 # B [7:0] $end
$var reg 2 $ S [1:0] $end
$scope module uut $end
$var wire 8 % A [7:0] $end
$var wire 8 & B [7:0] $end
$var wire 2 ' S [1:0] $end
$var wire 8 ( and_out [7:0] $end
$var wire 8 ) or_out [7:0] $end
$var wire 8 * sub_out [7:0] $end
$var wire 8 + add_out [7:0] $end
$var reg 8 , R [7:0] $end
$upscope $end
$upscope $end
$enddefinitions $end
$comment Show the parameter values. $end
$dumpall
$end
#0
$dumpvars
b1111 ,
b1111 +
b101 *
b1111 )
b0 (
b0 '
b101 &
b1010 %
b0 $
b101 #
b1010 "
b1111 !
$end
#10
b101 !
b101 ,
b1 $
b1 '
#20
b0 !
b0 ,
b10 $
b10 '
#30
b1111 !
b1111 ,
b11 $
b11 '
#40
b0 $
b0 '
b11 #
b11 &
b1111 +
b1001 *
b1100 "
b1100 %
#50
b1001 !
b1001 ,
b1 $
b1 '
#60
b0 !
b0 ,
b10 $
b10 '
#70
b1111 !
b1111 ,
b11 $
b11 '
#80
b1111 (
b11110 !
b11110 ,
b0 $
b0 '
b1111 #
b1111 &
b11110 +
b0 *
b1111 "
b1111 %
#90
b0 !
b0 ,
b1 $
b1 '
#100
b1111 !
b1111 ,
b10 $
b10 '
#110
b11 $
b11 '
